setup.py
funktown/__init__.py
funktown/dictionary.py
funktown/list.py
funktown/lookuptree.py
funktown/vector.py
funktown.egg-info/PKG-INFO
funktown.egg-info/SOURCES.txt
funktown.egg-info/dependency_links.txt
funktown.egg-info/top_level.txt