Metadata-Version: 1.0
Name: funktown
Version: 0.4.6
Summary: Functional Data Structures for Python
Home-page: http://github.com/zhemao/funktown
Author: Zhehao Mao
Author-email: zhehao.mao@gmail.com
License: UNKNOWN
Platform: UNKNOWN
